events_system/__init__.py
events_system/event_listener.py
events_system/events_system.py
events_system-0.0.4.dist-info/LICENCE
events_system-0.0.4.dist-info/METADATA
events_system-0.0.4.dist-info/WHEEL
events_system-0.0.4.dist-info/top_level.txt
events_system-0.0.4.dist-info/RECORD
