Metadata-Version: 2.1
Name: events-system
Version: 0.0.4
Summary: A singleton based thread-safe event system which components can use to subscribe and post to other components.
Author-email: sir even <sir_even@icloud.com>
Project-URL: Homepage, https://github.com/sirEven/event-system.git
Classifier: Programming Language :: Python :: 3
Classifier: License :: OSI Approved :: MIT License
Classifier: Operating System :: OS Independent
Requires-Python: >=3.7
License-File: LICENCE
